feathers/__init__.py
feathers/__main__.py
feathers/cache.py
feathers/demo.py
feathers/renderables/__init__.py
feathers/renderables/_divider.py
feathers/utils/__init__.py
feathers/utils/_errors.py
feathers/widgets/__init__.py
feathers/widgets/_cached_view.py
feathers/widgets/_nav_view.py
feathers/widgets/chat/__init__.py
feathers/widgets/chat/_chat.py
feathers/widgets/chat/_models.py
feathers/widgets/chat/_renderers.py
feathers/widgets/help/__init__.py
feathers/widgets/help/_base.py
feathers/widgets/help/_help.py
feathers/widgets/help/_long_help.py
feathers/widgets/help/_models.py
feathers/widgets/help/_short_help.py
feathers/widgets/help/_utils.py
feathers-0.1.4.dist-info/METADATA
feathers-0.1.4.dist-info/WHEEL
feathers-0.1.4.dist-info/RECORD
