Metadata-Version: 2.1
Name: feathers
Version: 0.1.4
Summary: Beautiful TUI components written on top of Textual
Home-page: https://github.com/shashanktomar/feathers
License: MIT
Keywords: textual,terminal,TUI
Author: Shashank Tomar
Author-email: shashank004@gmail.com
Requires-Python: >=3.8,<4.0
Classifier: License :: OSI Approved :: MIT License
Classifier: Programming Language :: Python :: 3
Classifier: Programming Language :: Python :: 3.8
Classifier: Programming Language :: Python :: 3.9
Classifier: Programming Language :: Python :: 3.10
Classifier: Programming Language :: Python :: 3.11
Requires-Dist: rich (>=13.3.5,<14.0.0)
Requires-Dist: textual (>=0.24.1,<0.25.0)
Project-URL: Repository, https://github.com/shashanktomar/feathers
